pasc/__init__.py
pasc/model.py
pasc/proxy.py
python_async_scrapestack_client-0.1.5.dist-info/LICENSE
python_async_scrapestack_client-0.1.5.dist-info/METADATA
python_async_scrapestack_client-0.1.5.dist-info/WHEEL
python_async_scrapestack_client-0.1.5.dist-info/RECORD
